granite/__init__.py
granite/model.py
granite/predict.py
granite/test_model.py
granite/trained_model.pkl
granite_qc-0.1.11.dist-info/METADATA
granite_qc-0.1.11.dist-info/WHEEL
granite_qc-0.1.11.dist-info/top_level.txt
granite_qc-0.1.11.dist-info/RECORD
