Metadata-Version: 2.1
Name: granite-qc
Version: 0.1.11
Summary: A package for graph-based energy optimization using a trained model.
Home-page: https://github.com/quocbao0603/granite
Author: Bao Tran
Author-email: tranq3@vcu.edu
License: UNKNOWN
Platform: UNKNOWN
Classifier: Programming Language :: Python :: 3
Classifier: License :: OSI Approved :: MIT License
Classifier: Operating System :: OS Independent
Requires-Python: >=3.6
Requires-Dist: torch
Requires-Dist: torch-geometric
Requires-Dist: networkx
Requires-Dist: numpy
